eradiate_mitsuba-0.3.2.dist-info/RECORD
eradiate_mitsuba-0.3.2.dist-info/WHEEL
eradiate_mitsuba-0.3.2.dist-info/entry_points.txt
eradiate_mitsuba-0.3.2.dist-info/top_level.txt
eradiate_mitsuba-0.3.2.dist-info/METADATA
eradiate_mitsuba-0.3.2.dist-info/licenses/LICENSE
mitsuba/libmitsuba.dylib
mitsuba/mitsuba_scalar_mono_double_ext.cpython-39-darwin.so
mitsuba/mitsuba_llvm_ad_rgb_ext.cpython-39-darwin.so
mitsuba/libjpeg-mitsuba.dylib
mitsuba/config.py
mitsuba/__init__.pyi
mitsuba/libImath-mitsuba.dylib
mitsuba/mitsuba_scalar_mono_ext.cpython-39-darwin.so
mitsuba/libIexMath-mitsuba.dylib
mitsuba/libIex-mitsuba.dylib
mitsuba/__init__.py
mitsuba/libIlmImfUtil-mitsuba.dylib
mitsuba/mitsuba_scalar_rgb_ext.cpython-39-darwin.so
mitsuba/mitsuba_scalar_mono_polarized_double_ext.cpython-39-darwin.so
mitsuba/libasmjit-mitsuba.dylib
mitsuba/libpugixml.dylib
mitsuba/py.typed
mitsuba/libIlmImf-mitsuba.dylib
mitsuba/mitsuba_scalar_spectral_ext.cpython-39-darwin.so
mitsuba/mitsuba_scalar_mono_polarized_ext.cpython-39-darwin.so
mitsuba/libpng-mitsuba.dylib
mitsuba/mitsuba
mitsuba/libIlmThread-mitsuba.dylib
mitsuba/mitsuba_ext.cpython-39-darwin.so
mitsuba/libHalf-mitsuba.dylib
mitsuba/stubs/scalar_mono_polarized_double_warp.pyi
mitsuba/stubs/scalar_spectral_mueller.pyi
mitsuba/stubs/scalar_rgb_filesystem.pyi
mitsuba/stubs/llvm_ad_rgb_mueller.pyi
mitsuba/stubs/python_ad_largesteps.pyi
mitsuba/stubs/scalar_rgb.pyi
mitsuba/stubs/scalar_rgb_mueller.pyi
mitsuba/stubs/python_xml.pyi
mitsuba/stubs/scalar_rgb_util.pyi
mitsuba/stubs/scalar_spectral_warp.pyi
mitsuba/stubs/scalar_mono.pyi
mitsuba/stubs/python_ad_guiding.pyi
mitsuba/stubs/scalar_mono_warp.pyi
mitsuba/stubs/python_ad_projective.pyi
mitsuba/stubs/llvm_ad_rgb_warp.pyi
mitsuba/stubs/scalar_rgb_quad.pyi
mitsuba/stubs/llvm_ad_rgb.pyi
mitsuba/stubs/scalar_rgb_math.pyi
mitsuba/stubs/scalar_mono_double_spline.pyi
mitsuba/stubs/scalar_mono_polarized_quad.pyi
mitsuba/stubs/scalar_mono_polarized_spline.pyi
mitsuba/stubs/scalar_mono_polarized_double.pyi
mitsuba/stubs/scalar_mono_double_warp.pyi
mitsuba/stubs/python_math.pyi
mitsuba/stubs/util.pyi
mitsuba/stubs/scalar_mono_polarized_double_spline.pyi
mitsuba/stubs/scalar_mono_polarized_double_mueller.pyi
