Metadata-Version: 2.1
Name: eradiate_mitsuba
Version: 0.3.2
Summary: 3: A Retargetable Forward and Inverse Renderer
Home-page: https://github.com/mitsuba-renderer/mitsuba3
Author: Realistic Graphics Lab (RGL), EPFL
Author-email: wenzel.jakob@epfl.ch
License: BSD
Requires-Python: >=3.8
License-File: LICENSE
Requires-Dist: drjit==0.4.6
